rlmolecule/__init__.py
rlmolecule/_version.py
rlmolecule/actors.py
rlmolecule/builder.py
rlmolecule/gdb_filters.py
rlmolecule/molecule_model.py
rlmolecule/molecule_state.py
rlmolecule/examples/__init__.py
rlmolecule/examples/logp.py
rlmolecule/examples/qed.py
rlmolecule/policy/__init__.py
rlmolecule/policy/model.py
rlmolecule/policy/preprocessor.py
rlmolecule/policy/data/__init__.py
rlmolecule/policy/data/preprocessor.json
tests/__init__.py
tests/conftest.py
tests/test_builder.py
tests/test_logp.py
tests/test_molecule_policy.py
tests/test_molecule_state.py
tests/test_ppo.py
rlmolecule-0.0.10.dist-info/LICENSE
rlmolecule-0.0.10.dist-info/METADATA
rlmolecule-0.0.10.dist-info/WHEEL
rlmolecule-0.0.10.dist-info/top_level.txt
rlmolecule-0.0.10.dist-info/RECORD
