Metadata-Version: 2.1
Name: rlmolecule
Version: 0.0.10
Summary: Reinforcement learning for molecular optimization
License: BSD 3-Clause License
Classifier: License :: OSI Approved :: BSD License
Classifier: Programming Language :: Python :: 3
License-File: LICENSE
Requires-Dist: graphenv
Requires-Dist: tensorflow <2.16,>=2.10
Requires-Dist: pylru
Requires-Dist: rdkit
Requires-Dist: nfp
Provides-Extra: dev
Requires-Dist: pytest ; extra == 'dev'
Requires-Dist: alfabet ; extra == 'dev'
Requires-Dist: pooch ; extra == 'dev'
